pypipo/__init__.py
pypipo/__main__.py
pypipo/__version__.py
pypipo/cli.py
pypipo/convert.py
pypipo/libs/__init__.py
pypipo/libs/imageProcessing.py
pypipo/libs/process.py
pypipo/libs/temp.py
pypipo/libs/utils.py
pypipo-0.0.9.dist-info/LICENSE
pypipo-0.0.9.dist-info/METADATA
pypipo-0.0.9.dist-info/WHEEL
pypipo-0.0.9.dist-info/entry_points.txt
pypipo-0.0.9.dist-info/top_level.txt
pypipo-0.0.9.dist-info/RECORD
