Metadata-Version: 2.1
Name: pypipo
Version: 0.0.9
Summary: Image convert to PIPO painting canvas automatically.
Home-page: https://github.com/AutoPipo/pypipo/
Author: ('Minku-Koo', 'Jiyong-Park')
Author-email: corleone@kakao.com
License: MIT License
Keywords: pipo painting,image painting,image processing,computer vision
Classifier: Programming Language :: Python :: 3.6
Classifier: Programming Language :: Python :: 3.7
License-File: LICENSE
Requires-Dist: numpy >=1.24.3
Requires-Dist: opencv-python >=4.7.0
Requires-Dist: multiprocessing-generator >=0.3
Requires-Dist: tqdm >=4.65.0
Requires-Dist: scipy >=1.10.1
Requires-Dist: click >=8.1.3
